mds/__init__.py
mds/admin.py
mds/apps.py
mds/db_helpers.py
mds/enums.py
mds/factories.py
mds/models.py
mds/provider_mapping.py
mds/urls.py
mds/utils.py
mds/access_control/__init__.py
mds/access_control/auth_means.py
mds/access_control/authenticate.py
mds/access_control/jwt_decode.py
mds/access_control/permissions.py
mds/access_control/scopes.py
mds/access_control/stateless_jwt.py
mds/apis/__init__.py
mds/apis/schema.py
mds/apis/utils.py
mds/apis/agency_api/__init__.py
mds/apis/agency_api/v0_3/__init__.py
mds/apis/agency_api/v0_3/compliances.py
mds/apis/agency_api/v0_3/geographies.py
mds/apis/agency_api/v0_3/policies.py
mds/apis/agency_api/v0_3/service_areas.py
mds/apis/agency_api/v0_3/urls.py
mds/apis/agency_api/v0_3/vehicles.py
mds/apis/agency_api/v0_x/__init__.py
mds/apis/agency_api/v0_x/compliances.py
mds/apis/agency_api/v0_x/geographies.py
mds/apis/agency_api/v0_x/policies.py
mds/apis/agency_api/v0_x/service_areas.py
mds/apis/agency_api/v0_x/urls.py
mds/apis/agency_api/v0_x/vehicles.py
mds/authent/__init__.py
mds/authent/apps.py
mds/authent/generators.py
mds/authent/models.py
mds/authent/oauth2_provider_apps.py
mds/authent/oauthlib_utils.py
mds/authent/public_api.py
mds/authent/settings.py
mds/authent/urls.py
mds/authent/migrations/0001_squashed_0007_post_make_application_user_scope_blankable.py
mds/authent/migrations/__init__.py
mds/fixtures/ladot.yaml
mds/locale/en_US/LC_MESSAGES/django.mo
mds/locale/en_US/LC_MESSAGES/django.po
mds/locale/fr_FR/LC_MESSAGES/django.mo
mds/locale/fr_FR/LC_MESSAGES/django.po
mds/management/commands/genfixture.py
mds/management/commands/poll_providers.py
mds/migrations/0001_squashed_0059_post_policy_config_encoder.py
mds/migrations/0002_pre_compliance_extra.py
mds/migrations/0003_post_index_device_events.py
mds/migrations/__init__.py
mds/provider_poller/__init__.py
mds/provider_poller/oauth2_store.py
mds/provider_poller/poller.py
mds/provider_poller/settings.py
mds/provider_poller/translation.py
mds/templates/swagger.html
django_mds-0.7.9.dist-info/LICENSE
django_mds-0.7.9.dist-info/METADATA
django_mds-0.7.9.dist-info/WHEEL
django_mds-0.7.9.dist-info/top_level.txt
django_mds-0.7.9.dist-info/zip-safe
django_mds-0.7.9.dist-info/RECORD
