Metadata-Version: 2.1
Name: django-mds
Version: 0.7.9
Summary: MDS Agency implementation
Home-page: http://github.com/Polyconseil/django-mds
Author: Polyconseil
Author-email: opensource+django-mds@polyconseil.fr
License: MIT
Keywords: Mobility City MDS MaaS Django
Platform: UNKNOWN
Classifier: Development Status :: 3 - Alpha
Classifier: Intended Audience :: Other Audience
Classifier: License :: OSI Approved :: MIT License
Classifier: Natural Language :: English
Classifier: Operating System :: OS Independent
Classifier: Environment :: Web Environment
Classifier: Programming Language :: Python :: 3
Classifier: Programming Language :: Python :: 3.7
Classifier: Topic :: Other/Nonlisted Topic
Classifier: Framework :: Django
Requires-Dist: coreapi
Requires-Dist: cryptography
Requires-Dist: django (<3.0)
Requires-Dist: django-filter
Requires-Dist: django-cors-headers
Requires-Dist: django-oauth-toolkit
Requires-Dist: djangorestframework (==3.9.3)
Requires-Dist: drf-yasg (==1.16.0)
Requires-Dist: getconf
Requires-Dist: psycopg2
Requires-Dist: pyjwt
Requires-Dist: pyyaml
Requires-Dist: requests-oauthlib
Requires-Dist: retrying
Requires-Dist: semantic-version
Provides-Extra: dev
Requires-Dist: black ; extra == 'dev'
Requires-Dist: factory-boy ; extra == 'dev'
Requires-Dist: flake8 ; extra == 'dev'
Requires-Dist: pytest ; extra == 'dev'
Requires-Dist: pytest-django ; extra == 'dev'
Requires-Dist: requests-mock ; extra == 'dev'
Requires-Dist: zest.releaser[recommended] ; extra == 'dev'
Requires-Dist: polydev.github ; extra == 'dev'
